tameris/__init__.py
tameris/commands/__init__.py
tameris/commands/command.py
tameris/commands/context.py
tameris/core/__init__.py
tameris/core/client.py
tameris/core/event_handler.py
tameris/core/extensions.py
tameris/core/request_handler.py
tameris/models/__init__.py
tameris/models/attachment.py
tameris/models/channel.py
tameris/models/embed.py
tameris/models/emoji.py
tameris/models/guild.py
tameris/models/guild_member.py
tameris/models/invite.py
tameris/models/member.py
tameris/models/message.py
tameris/models/permissions.py
tameris/models/role.py
tameris/models/template.py
tameris/models/voice.py
tameris/models/webhook.py
tameris-0.1.1.dist-info/LICENSE
tameris-0.1.1.dist-info/METADATA
tameris-0.1.1.dist-info/WHEEL
tameris-0.1.1.dist-info/top_level.txt
tameris-0.1.1.dist-info/RECORD
