Metadata-Version: 2.1
Name: tameris
Version: 0.1.1
Summary: A Python Discord API Wrapper based around customizability and expandability!
Home-page: https://github.com/erick-dsnk/tameris
Author: Tabacaru Eric
Author-email: erick.8bld@gmail.com
License: UNKNOWN
Platform: UNKNOWN
Classifier: Programming Language :: Python :: 3
Classifier: Development Status :: 3 - Alpha
Classifier: License :: OSI Approved :: Apache Software License
Classifier: Operating System :: OS Independent
Requires-Python: >=3.5
